src/__init__.py
src/arabic_utility/__init__.py
src/arabic_utility/arbchar_util.py
src/arabic_utility/diac_util.py
src/arabic_utility/num_util.py
src/arabic_utility/punc_util.py
src/preprocessing/__init__.py
src/preprocessing/text_content.py
src/preprocessing/text_structure.py
src/preprocessing/text_verification.py
Tahdheeb-0.1.1.dist-info/LICENSE
Tahdheeb-0.1.1.dist-info/METADATA
Tahdheeb-0.1.1.dist-info/WHEEL
Tahdheeb-0.1.1.dist-info/top_level.txt
Tahdheeb-0.1.1.dist-info/RECORD
