Metadata-Version: 2.1
Name: Tahdheeb
Version: 0.1.1
Summary: An Arabic Preprocessing Toolkit for Pretraining of LLM
Home-page: https://github.com/ehsanasgari/Tahdheeb
Author: Ehsaneddin Asgari and Yassine Elkheir
Author-email: Ehsaneddin Asgari and Yassine Elkheir <easgari@hbku.edu.qa>
Project-URL: Homepage, https://github.com/ehsanasgari/Tahdheeb
Project-URL: Issues, https://github.com/ehsanasgari/Tahdheeb/issues
Classifier: Programming Language :: Python :: 3
Classifier: License :: OSI Approved :: MIT License
Classifier: Operating System :: OS Independent
Requires-Python: >=3.6
License-File: LICENSE
